{"id":117502,"xmlId":"com.github.jensim.megamanipulator","name":"mega-manipulator","description":"\n<h1><b>Mega Manipulator (m²)</b></h1>\n\n\n<p>\nOne stop shop for making changes, big or small, in a lot of places at once.\nSee this as an alternative to sourcegraph campaigns, without the docker layer in between you, and the changes you want to make.\n</p>\n\n\n<p>\nUse sourcegraph queries to find target repos.\nThen a forEach approach is provided for eache of the following actions:\nApply changes (using scripts),\nCommit,\nPush,\nFork (lazy, eager, never),\nPR.\n</p>\n\n\n<p></p><h2><b>Search</b></h2><p></p>\n\n<p>Connect to any number of search hosts, and queury those for repository hits<br>\nClone the found repos to local file system, and inspect/plan the change you want to make</p>\n\n<p></p><h2><b>Apply changes</b></h2><p></p>\n\n<p>Run scripted changes defined in <code>mega-manipulator.bash</code>, or apply changes from the terminal, or manually, whatever fits\nyou best.</p>\n\n<p></p><h2><b>Draft PRs</b></h2><p></p>\n\n<p>The file system structure of the clones link back to the config defined in <code>mega-manipulator.yml</code>, so we are able to\ndraft PRs for all code hosts you have cloned from. It doesn't even have to have been discovered using the same search\nhost.<br>\nOnce you have created your PRs, you are also able to edit them, or decline, in batches.</p>\n\n<p></p><h2><b>Profit</b></h2><p></p>\n\n<p>Spend less time making small, or big, changes</p>\n\n","tags":["Code tools","Tools integration","Search and replace","Refactoring","Code editing"],"vendor":"jensim","version":"0.0.14","notes":"<h3>Added</h3>\n<ul><li>Fuzzy search open PRs</li></ul>\n\n<h3>Changed</h3>\n\n<h3>Deprecated</h3>\n\n<h3>Removed</h3>\n\n<h3>Fixed</h3>","dependencies":["com.intellij.modules.platform"],"since":"202.0","until":"211.*","size":16593626}